CHANGELOG.txt
MANIFEST.in
README.txt
TODO.txt
ez_setup.py
setup.py
mm2notes/__init__.py
mm2notes/mm2notes.py
mm2notes.egg-info/PKG-INFO
mm2notes.egg-info/SOURCES.txt
mm2notes.egg-info/dependency_links.txt
mm2notes.egg-info/top_level.txt
scripts/mm2notes