Metadata-Version: 1.0
Name: mm2notes
Version: 0.1.1
Summary: Convert a FreeMind mind-map (mm) into a meeting notes (html/txt).
Home-page: http://code.google.com/p/mm2notes
Author: Scott Kirkwood
Author-email: scott@forusers.com
License: Apache 2.0
Download-URL: http://mm2notes.googlecode.com/files/mm2notes-0.1.1.zip
Keywords: mm,FreeMind,notes,XML,text,meeting,Python
Platform: POSIX
Platform: Windows
Classifier: Development Status :: 2 - Pre-Alpha
Classifier: Environment :: Console
Classifier: Intended Audience :: Developers
Classifier: Intended Audience :: Information Technology
Classifier: License :: OSI Approved :: Apache Software License
Classifier: Operating System :: OS Independent
Classifier: Operating System :: Microsoft :: Windows
Classifier: Operating System :: POSIX
Classifier: Programming Language :: Python
Classifier: Topic :: Documentation
Classifier: Topic :: Software Development :: Code Generators
Classifier: Topic :: Text Processing :: Markup :: XML
Classifier: Topic :: Utilities
